mortgage/Expenses.py
mortgage/MonthlyROI.py
mortgage/MontlyROI.py
mortgage/Mortgage.py
mortgage/MortgageStatement.py
mortgage/ROI.py
mortgage/TermScheduler.py
mortgage/__init__.py
pymortgage-0.1.6.dist-info/LICENSE
pymortgage-0.1.6.dist-info/METADATA
pymortgage-0.1.6.dist-info/WHEEL
pymortgage-0.1.6.dist-info/top_level.txt
pymortgage-0.1.6.dist-info/RECORD
