Metadata-Version: 2.1
Name: pymortgage
Version: 0.1.6
Summary: Python Mortgage utilities
Home-page: https://github.com/droopy4096/pymortgage
Author: Dmytro Makovey
Author-email: dmakovey@yahoo.com
License: GPL3
Keywords: mortgage library
Platform: UNKNOWN
Classifier: Development Status :: 4 - Beta
Classifier: Topic :: Software Development :: Libraries :: Python Modules
Classifier: License :: OSI Approved :: GNU General Public License v3 (GPLv3)
